fourbit-ripple-up-counter.srcs/sources_1/new/four_bit_ripple_up_counter.v
`timescale 1ns / 1ps
//////////////////////////////////////////////////////////////////////////////////
// Company: 
// Engineer: 
// 
// Create Date: 22.07.2025 20:03:23
// Design Name: 
// Module Name: four_bit_ripple_up_counter
// Project Name: 
// Target Devices: 
// Tool Versions: 
// Description: 
// 
// Dependencies: 
// 
// Revision:
// Revision 0.01 - File Created
// Additional Comments:
// 
//////////////////////////////////////////////////////////////////////////////////


module four_bit_ripple_up_counter(q,qbar,clk,reset);
    output [3:0] q,qbar;
    input clk,reset;
    T_FF t0(q[0],qbar[0],clk,reset);
    T_FF t1(q[1],qbar[1],qbar[0],reset);
    T_FF t2(q[2],qbar[2],qbar[1],reset);
    T_FF t3(q[3],qbar[3],qbar[2],reset);
endmodule
module T_FF(q,qbar,clk,reset);
    output reg q;
    output qbar;
    input clk,reset;
    always@(posedge reset or posedge clk)
    begin
        if (reset)
            q <=1'b0;
        else
            q <= ~q;
    end
    assign qbar = ~q;
endmodule

fourbit-ripple-up-counter.srcs/sim_1/new/four_bit_ripple_up_counter_tb.v
`timescale 1ns / 1ps
//////////////////////////////////////////////////////////////////////////////////
// Company: 
// Engineer: 
// 
// Create Date: 22.07.2025 23:02:15
// Design Name: 
// Module Name: four_bit_ripple_up_counter_tb
// Project Name: 
// Target Devices: 
// Tool Versions: 
// Description: Testbench for 4-bit ripple up counter
// 
// Dependencies: four_bit_ripple_up_counter.v
// 
// Revision:
// Revision 0.01 - File Created
// Additional Comments:
// 
//////////////////////////////////////////////////////////////////////////////////

module four_bit_ripple_up_counter_tb;
    reg clk;
    reg reset;
    wire [3:0] q, qbar;

    // Instantiate the Unit Under Test (UUT)
    four_bit_ripple_up_counter uut (
        .q(q),
        .qbar(qbar),
        .clk(clk),
        .reset(reset)
    );

    // Clock generation
    initial clk = 1'b0;
    always #5 clk = ~clk;

    // Stimulus
    initial begin
        $dumpfile("ripple_carry_counter_tb.vcd");
        $dumpvars(0, four_bit_ripple_up_counter_tb);

        // Initial reset
        reset = 1'b1;
        #15 reset = 1'b0;  // Release reset
        #180 reset = 1'b1; // Assert reset again
        #20 reset = 1'b0;  // Release reset again

        $display("Test complete.");
        #20 $finish;
    end

    // Monitor values
    initial begin
        $monitor("Time: %0dns | q = %b | clk = %b | reset = %b", $time, q, clk, reset);
    end
endmodule

fourbit-ripple-up-counter.sim/sim_1/behav/xsim/ripple_carry_counter_tb.vcd
$date
   Tue Jul 22 23:58:47 2025
$end

$version
  2025.1.0
  $dumpfile ("ripple_carry_counter_tb.vcd") 
$end

$timescale
  1ps
$end

$scope module four_bit_ripple_up_counter_tb $end
$var reg 1 ! clk $end
$var reg 1 " reset $end
$var wire 4 # q [3:0] $end
$var wire 4 $ qbar [3:0] $end
$scope module uut $end
$var wire 4 # q [3:0] $end
$var wire 4 $ qbar [3:0] $end
$var wire 1 % clk $end
$var wire 1 & reset $end
$scope module t0 $end
$var reg 1 ' q $end
$var wire 1 ( qbar $end
$var wire 1 % clk $end
$var wire 1 & reset $end
$upscope $end
$scope module t1 $end
$var reg 1 ) q $end
$var wire 1 * qbar $end
$var wire 1 ( clk $end
$var wire 1 & reset $end
$upscope $end
$scope module t2 $end
$var reg 1 + q $end
$var wire 1 , qbar $end
$var wire 1 * clk $end
$var wire 1 & reset $end
$upscope $end
$scope module t3 $end
$var reg 1 - q $end
$var wire 1 . qbar $end
$var wire 1 , clk $end
$var wire 1 & reset $end
$upscope $end
$upscope $end
$upscope $end
$enddefinitions $end

#0
$dumpvars
0!
1"
b0 #
b1111 $
0%
1&
0'
1(
0)
1*
0+
1,
0-
1.
$end

#5000
1!
1%

#10000
0!
0%

#15000
1!
0"
b1 #
b1110 $
1%
0&
1'
0(

#20000
0!
0%

#25000
1!
b10 #
b1101 $
1%
0'
1(
1)
0*

#30000
0!
0%

#35000
1!
b11 #
b1100 $
1%
1'
0(

#40000
0!
0%

#45000
1!
b100 #
b1011 $
1%
0'
1(
0)
1*
1+
0,

#50000
0!
0%

#55000
1!
b101 #
b1010 $
1%
1'
0(

#60000
0!
0%

#65000
1!
b110 #
b1001 $
1%
0'
1(
1)
0*

#70000
0!
0%

#75000
1!
b111 #
b1000 $
1%
1'
0(

#80000
0!
0%

#85000
1!
b1000 #
b111 $
1%
0'
1(
0)
1*
0+
1,
1-
0.

#90000
0!
0%

#95000
1!
b1001 #
b110 $
1%
1'
0(

#100000
0!
0%

#105000
1!
b1010 #
b101 $
1%
0'
1(
1)
0*

#110000
0!
0%

#115000
1!
b1011 #
b100 $
1%
1'
0(

#120000
0!
0%

#125000
1!
b1100 #
b11 $
1%
0'
1(
0)
1*
1+
0,

#130000
0!
0%

#135000
1!
b1101 #
b10 $
1%
1'
0(

#140000
0!
0%

#145000
1!
b1110 #
b1 $
1%
0'
1(
1)
0*

#150000
0!
0%

#155000
1!
b1111 #
b0 $
1%
1'
0(

#160000
0!
0%

#165000
1!
b0 #
b1111 $
1%
0'
1(
0)
1*
0+
1,
0-
1.

#170000
0!
0%

#175000
1!
b1 #
b1110 $
1%
1'
0(

#180000
0!
0%

#185000
1!
b10 #
b1101 $
1%
0'
1(
1)
0*

#190000
0!
0%

#195000
1!
1"
b0 #
b1111 $
1%
1&
0)
1*

#200000
0!
0%

#205000
1!
1%

#210000
0!
0%

#215000
1!
0"
b1 #
b1110 $
1%
0&
1'
0(

#220000
0!
0%

#225000
1!
b10 #
b1101 $
1%
0'
1(
1)
0*
